MANIFEST.in
README.md
setup.py
django_wellbehaved/__init__.py
django_wellbehaved/bdd_testcase.py
django_wellbehaved/models.py
django_wellbehaved/runner.py
django_wellbehaved/tests.py
m3_wellbehaved.egg-info/PKG-INFO
m3_wellbehaved.egg-info/SOURCES.txt
m3_wellbehaved.egg-info/dependency_links.txt
m3_wellbehaved.egg-info/requires.txt
m3_wellbehaved.egg-info/top_level.txt