Metadata-Version: 1.1
Name: m3-wellbehaved
Version: 0.1.0.3
Summary: Rollback-enabled BDD wrapper for Django with i18n support
Home-page: http://src.bars-open.ru/py/m3/m3_contrib/django-wellbehaved
Author: Kirill Borisov
Author-email: borisov@bars-open.ru
License: UNKNOWN
Platform: UNKNOWN
Classifier: Programming Language :: Python :: 2.6
Classifier: Framework :: Django
Classifier: Development Status :: 3 - Alpha
Classifier: Intended Audience :: Developers
Classifier: License :: OSI Approved :: MIT License
Classifier: Topic :: Software Development :: Testing
